{"categories":{"0":true,"1":true},"docCount":{"0":11,"1":21},"totalDocuments":32,"vocabulary":{"0":true,"1":true,"2":true,"3":true,"4":true,"5":true,"6":true,"8":true,"9":true,"10":true,"11":true,"12":true,"13":true,"17":true,"18":true,"21":true,"22":true,"23":true,"25":true,"26":true,"29":true,"46":true,"54":true,"55":true,"85":true,"100":true,"107":true,"155":true,"500":true,"2015":true,"2018":true,"":true,"Rita_2110":true,"DrAVSriv":true,"INCIndia":true,"The":true,"day":true,"Modiji":true,"will":true,"say":true,"Mere":true,"crore":true,"hindus":true,"bharatwasi":true,"minus":true,"mullas":true,"n":true,"moulvi":true,"a":true,"earthquake":true,"for":true,"sure":true,"creating":true,"proof":true,"structures":true,"https":true,"t":true,"co":true,"ibueHjpPBL":true,"Possibilities":true,"horrified":true,"Earthquake":true,"soon":true,"Repeat":true,"of":true,"previous":true,"iranIraq":true,"in":true,"different":true,"place":true,"within":true,"iXBIkiMHUd":true,"RT":true,"IDRCinAsia":true,"devastating":true,"Nepal":true,"destroyed":true,"hundreds":true,"thousands":true,"homes":true,"With":true,"our":true,"support":true,"icimod":true,"provided":true,"assis":true,"IEEEorg":true,"Seven":true,"years":true,"after":true,"powerful":true,"and":true,"tsunami":true,"caused":true,"massive":true,"nuclear":true,"meltdown":true,"Daiichi":true,"Power":true,"Plant":true,"robots":true,"are":true,"comi":true,"Siemens_Energy":true,"Join":true,"TranspowerNZ":true,"project":true,"director":true,"Andrew":true,"Gard":true,"at":true,"the":true,"company":true,"s":true,"resistent":true,"HVDC":true,"link":true,"bNFfOzXD":true,"SuperStry":true,"Imagine":true,"being":true,"next":true,"to":true,"this":true,"during":true,"an":true,"aASnjenIMB":true,"city":true,"engineers":true,"concerned":true,"that":true,"many":true,"buildings":true,"not":true,"strong":true,"enough":true,"withstand":true,"major":true,"[900":true,"020]":true,"(":true,")":true,"M4":true,"strikes":true,"km":true,"SE":true,"Leh":true,"India)":true,"min":true,"ago":true,"More":true,"info":true,"x6RS2crjGn":true,"KASHMIR":true,"XIZANG":true,"BORDER":true,"REGION":true,"Nov":true,"09":true,"00":true,"UTC":true,"report":true,"pAByfjb3hK":true,"EarthquakePH":true,"EarthquakeDavaoOriental":true,"Information":true,"No":true,"Date":true,"Time":true,"05":true,"06":true,"PM":true,"Magnitude":true,"0ho9gNT87d":true,"[":true,"Reporte":true,"Sísmico":true,"]":true,"Light":true,"mag":true,"on":true,"Thursday":true,"November":true,"d6T5e6fOuD":true,"magnitude":true,"from":true,"Valdez":true,"AK":true,"United":true,"States":true,"yckQRCZ8rw":true,"occurred":true,"near":true,"Kashmir":true,"xizang":true,"Border":true,"Region":true,"CLBHdRR7US":true,"A":true,"has":true,"Kantens":true,"GR":true,"Netherlands":true,"AM":true,"7bvbs1XUJ1":true,"276km":true,"Kodiak":true,"Alaska":true,"JL58D7YNDI":true,"oB6tVerpVg":true,"(G":true,"apMg2Ye0w2":true,"NGMAhxeJJB":true,"Minor":true,"GULF":true,"OF":true,"ALASKA":true,"VolcanoDiscovery":true,"ohaqCjOZ75":true,"vyYZyakJ44":true,"Hits":true,"286km":true,"gxcMavUjgP":true,"EQYpBoByJm":true,"New":true,"(Mb)":true,"Xizang":true,"border":true,"App":true,"e1jlc9uim5":true,"Temblor":true,"SCLmjUb6sM":true,"top":true,"story":true,"Hacker":true,"News":true,"Strange":true,"waves":true,"rippled":true,"around":true,"Earth":true,"8CptRkhRCO":true,"Over":true,"Hurt":true,"Western":true,"Iran":true,"Mb15gtK2mK":true,"Latest_News":true,"Earthquakes0":true,"hit":true,"Suni":true,"Ufe":true,"(Nitibe)":true,"East":true,"Timor":true,"0km":true,"GMT+4":true,"(EMSC)":true,"MndTuL2iae":true,"EMSC":true,"séisme)":true,"M2":true,"Pau":true,"France)":true,"ln5v2bwJ0V":true,"Update":true,"M3":true,"terremoto)":true,"Úbeda":true,"Spain)":true,"69X3Jzudvv":true,"phivolcs_dost":true,"USGS":true,"reports":true,"M1":true,"8km":true,"NE":true,"Aguanga":true,"CA":true,"XVV1m7YUdO":true,"quake":true,"46km":true,"N":true,"bSoywJ1Wk8":true},"vocabularySize":284,"wordCount":{"0":199,"1":441},"wordFrequencyCount":{"0":{"1":1,"2":1,"107":1,"2015":1,"":5,"Rita_2110":1,"DrAVSriv":1,"INCIndia":1,"The":3,"day":1,"Modiji":1,"will":1,"say":1,"Mere":1,"crore":1,"hindus":1,"bharatwasi":1,"minus":1,"mullas":1,"n":1,"moulvi":1,"a":4,"earthquake":11,"for":2,"sure":1,"creating":1,"proof":1,"structures":1,"https":7,"t":7,"co":7,"ibueHjpPBL":1,"Possibilities":1,"horrified":1,"Earthquake":1,"soon":1,"Repeat":1,"of":4,"previous":1,"iranIraq":1,"in":3,"different":1,"place":1,"within":1,"iXBIkiMHUd":1,"RT":7,"IDRCinAsia":1,"devastating":1,"Nepal":1,"destroyed":1,"hundreds":1,"thousands":1,"homes":1,"With":1,"our":1,"support":1,"icimod":1,"provided":1,"assis":1,"IEEEorg":1,"Seven":1,"years":1,"after":1,"powerful":1,"and":1,"tsunami":1,"caused":1,"massive":1,"nuclear":1,"meltdown":1,"Daiichi":1,"Power":1,"Plant":1,"robots":1,"are":3,"comi":1,"Siemens_Energy":2,"Join":2,"TranspowerNZ":2,"project":2,"director":2,"Andrew":2,"Gard":2,"at":2,"the":3,"company":2,"s":2,"resistent":2,"HVDC":2,"link":2,"bNFfOzXD":2,"SuperStry":3,"Imagine":3,"being":3,"next":3,"to":4,"this":3,"during":3,"an":3,"aASnjenIMB":3,"city":1,"engineers":1,"concerned":1,"that":1,"many":1,"buildings":1,"not":1,"strong":1,"enough":1,"withstand":1,"major":1,"[900":1,"020]":1},"1":{"0":4,"1":3,"2":3,"3":9,"4":5,"5":4,"6":1,"8":1,"9":3,"10":1,"11":5,"12":1,"13":1,"17":2,"18":3,"21":1,"22":1,"23":2,"25":3,"26":1,"29":10,"46":1,"54":1,"55":1,"85":1,"100":1,"155":1,"500":1,"2018":5,"":5,"Earthquake":10,"(":8,")":1,"M4":3,"strikes":5,"km":5,"SE":6,"of":8,"Leh":1,"India)":1,"min":5,"ago":5,"More":2,"info":3,"https":25,"t":25,"co":25,"x6RS2crjGn":1,"KASHMIR":3,"XIZANG":3,"BORDER":3,"REGION":3,"Nov":3,"09":4,"00":4,"UTC":4,"report":1,"pAByfjb3hK":1,"EarthquakePH":2,"EarthquakeDavaoOriental":2,"Information":2,"No":2,"Date":2,"and":2,"Time":2,"05":2,"06":2,"PM":2,"Magnitude":5,"0ho9gNT87d":1,"[":1,"Reporte":1,"Sísmico":1,"]":1,"Light":1,"mag":2,"earthquake":12,"on":5,"Thursday":3,"November":3,"d6T5e6fOuD":1,"magnitude":2,"from":1,"Valdez":2,"AK":1,"United":1,"States":1,"yckQRCZ8rw":1,"occurred":2,"near":2,"Kashmir":2,"xizang":1,"Border":1,"Region":1,"at":3,"CLBHdRR7US":1,"A":1,"has":2,"Kantens":1,"GR":1,"Netherlands":1,"AM":2,"7bvbs1XUJ1":1,"276km":1,"Kodiak":2,"Alaska":3,"JL58D7YNDI":1,"oB6tVerpVg":1,"(G":1,"apMg2Ye0w2":1,"NGMAhxeJJB":1,"Minor":2,"GULF":1,"OF":1,"ALASKA":1,"VolcanoDiscovery":1,"ohaqCjOZ75":1,"vyYZyakJ44":1,"Hits":1,"286km":1,"gxcMavUjgP":1,"EQYpBoByJm":1,"New":2,"(Mb)":1,"Xizang":1,"border":1,"App":1,"e1jlc9uim5":1,"Temblor":1,"SCLmjUb6sM":1,"top":1,"story":1,"Hacker":1,"News":2,"Strange":1,"waves":1,"rippled":1,"around":1,"Earth":1,"8CptRkhRCO":1,"Over":1,"Hurt":1,"in":2,"Western":1,"Iran":1,"Mb15gtK2mK":1,"Latest_News":1,"RT":4,"Earthquakes0":1,"hit":1,"Suni":1,"Ufe":1,"(Nitibe)":1,"East":1,"Timor":1,"0km":1,"GMT+4":1,"(EMSC)":1,"MndTuL2iae":1,"EMSC":2,"séisme)":1,"M2":1,"Pau":1,"France)":1,"ln5v2bwJ0V":1,"Update":2,"M3":2,"terremoto)":2,"Úbeda":2,"Spain)":2,"69X3Jzudvv":2,"phivolcs_dost":1,"USGS":2,"reports":2,"a":2,"M1":2,"8km":1,"NE":1,"Aguanga":1,"CA":1,"XVV1m7YUdO":1,"quake":2,"46km":1,"N":1,"bSoywJ1Wk8":1}},"options":{}}
